vtkplotlib/__init__.py
vtkplotlib/_get_vtk.py
vtkplotlib/_history.py
vtkplotlib/_image_io.py
vtkplotlib/_interactive.py
vtkplotlib/_matplotlib_colors.py
vtkplotlib/_version.py
vtkplotlib/_vtk.py
vtkplotlib/_vtk_errors.py
vtkplotlib/colors.py
vtkplotlib/geometry.py
vtkplotlib/image_io.py
vtkplotlib/interactive.py
vtkplotlib/nuts_and_bolts.py
vtkplotlib/unicode_paths.py
vtkplotlib/__PyInstaller/hook-vtkplotlib.py
vtkplotlib/data/__init__.py
vtkplotlib/data/icons/Back.jpg
vtkplotlib/data/icons/Bottom.jpg
vtkplotlib/data/icons/Front.jpg
vtkplotlib/data/icons/Left.jpg
vtkplotlib/data/icons/Right.jpg
vtkplotlib/data/icons/Top.jpg
vtkplotlib/data/icons/screenshot.png
vtkplotlib/data/models/rabbit/LICENSE.txt
vtkplotlib/data/models/rabbit/README.txt
vtkplotlib/data/models/rabbit/attribution_card.html
vtkplotlib/data/models/rabbit/rabbit.stl
vtkplotlib/figures/BaseFigure.py
vtkplotlib/figures/QtFigure.py
vtkplotlib/figures/__init__.py
vtkplotlib/figures/figure.py
vtkplotlib/figures/figure_manager.py
vtkplotlib/figures/QtGuiFigure/__init__.py
vtkplotlib/figures/QtGuiFigure/cursor_tracker.py
vtkplotlib/plots/Arrow.py
vtkplotlib/plots/BasePlot.py
vtkplotlib/plots/Legend.py
vtkplotlib/plots/Lines.py
vtkplotlib/plots/MeshPlot.py
vtkplotlib/plots/Polygon.py
vtkplotlib/plots/ScalarBar.py
vtkplotlib/plots/Scatter.py
vtkplotlib/plots/Surface.py
vtkplotlib/plots/Text.py
vtkplotlib/plots/Text3D.py
vtkplotlib/plots/__init__.py
vtkplotlib/plots/imshow.py
vtkplotlib/plots/polydata.py
vtkplotlib-2.1.0.dist-info/LICENSE.txt
vtkplotlib-2.1.0.dist-info/METADATA
vtkplotlib-2.1.0.dist-info/WHEEL
vtkplotlib-2.1.0.dist-info/entry_points.txt
vtkplotlib-2.1.0.dist-info/top_level.txt
vtkplotlib-2.1.0.dist-info/RECORD
